setup.py
kyu_ar_kowd_jenereytor/__init__.py
kyu_ar_kowd_jenereytor/exceptions.py
kyu_ar_kowd_jenereytor.egg-info/PKG-INFO
kyu_ar_kowd_jenereytor.egg-info/SOURCES.txt
kyu_ar_kowd_jenereytor.egg-info/dependency_links.txt
kyu_ar_kowd_jenereytor.egg-info/top_level.txt