Metadata-Version: 1.0
Name: kyu-ar-kowd-jenereytor
Version: 1.0
Summary: Python script to generate QR Code using Google Chart Tool
Home-page: http://ferdinandsilva.com
Author: Ferdinand Silva
Author-email: ferdinandsilva@ferdinandsilva.com
License: UNKNOWN
Download-URL: https://github.com/six519/Kyu_Ar_Kowd_Jenereytor
Platform: UNKNOWN
Classifier: Development Status :: 4 - Beta
Classifier: Intended Audience :: Developers
Classifier: Natural Language :: English
Classifier: Programming Language :: Python
Classifier: License :: Freeware
